XSsolar.py
XSsolar-0.8.dist-info/LICENSE
XSsolar-0.8.dist-info/METADATA
XSsolar-0.8.dist-info/WHEEL
XSsolar-0.8.dist-info/top_level.txt
XSsolar-0.8.dist-info/RECORD
