Metadata-Version: 2.1
Name: XSsolar
Version: 0.8
Summary: Communication for Mastervolt inverters
Home-page: https://github.com/kloknibor/XSsolar
Author: Jorg Janssen & Robin Kolk 
Author-email: robinkolk@msn.com
License: UNKNOWN
Platform: UNKNOWN
Classifier: Programming Language :: Python :: 3
Classifier: License :: OSI Approved :: MIT License
Classifier: Operating System :: OS Independent
